netallocation/__init__.py
netallocation/breakdown.py
netallocation/common.py
netallocation/convert.py
netallocation/cost.py
netallocation/evaluate.py
netallocation/flow.py
netallocation/grid.py
netallocation/io.py
netallocation/linalg.py
netallocation/plot.py
netallocation/plot_helpers.py
netallocation/process.py
netallocation/test.py
netallocation/utils.py
netallocation/networks/ac_dc.h5
netallocation/networks/european_model.h5
netallocation/networks/mini_model.h5
netallocation/networks/simple_dc_model.h5
netallocation/package_data/color_config.yaml
netallocation-0.0.8.dist-info/METADATA
netallocation-0.0.8.dist-info/WHEEL
netallocation-0.0.8.dist-info/top_level.txt
netallocation-0.0.8.dist-info/RECORD
