Metadata-Version: 2.1
Name: netallocation
Version: 0.0.8
Summary: Package for allocating flows and costs in a PyPSA network
Home-page: https://github.com/FRESNA/netallocation
Author: Fabian Hofmann (FIAS)
Author-email: hofmann@fias.uni-frankfurt.de
License: GPLv3
Platform: UNKNOWN
Classifier: Environment :: Console
Classifier: Intended Audience :: Science/Research
Classifier: License :: OSI Approved :: GNU General Public License v3 or later (GPLv3+)
Classifier: Natural Language :: English
Classifier: Operating System :: OS Independent
Requires-Dist: pypsa
Requires-Dist: pandas (>=1.0)
Requires-Dist: pyyaml
Requires-Dist: xarray (>=0.15)
Requires-Dist: progressbar2
Requires-Dist: sparse
Requires-Dist: dask
Requires-Dist: h5py
Requires-Dist: scipy
Requires-Dist: geopandas
Requires-Dist: pyyaml (>=5.0)
Requires-Dist: netcdf4
Provides-Extra: docs
Requires-Dist: sphinx (>=1.4) ; extra == 'docs'
Requires-Dist: sphinx-rtd-theme ; extra == 'docs'
